string_flipper/__init__.py
string_flipper/flipper.py
string_flipper-0.1.dist-info/METADATA
string_flipper-0.1.dist-info/WHEEL
string_flipper-0.1.dist-info/top_level.txt
string_flipper-0.1.dist-info/RECORD
