Metadata-Version: 2.1
Name: string_flipper
Version: 0.1
Summary: A tiny Python library to flip (reverse) strings.
Home-page: https://pypi.org/project/string_flipper/
Author: Your Name
Requires-Python: >=3.6
